{
  "exclusionRules": [
    {},
    {},
    {},
    {},
    {},
    {},
    {},
    {},
    {},
    {}
  ],
  "filterLinkHints": true,
  "grabBackFocus": true,
  "keyMappings": "# ═══════════════════════════════════════════════════════════════\n#   Carlisia's Vimium Config\n#   Mapped from Neovim muscle memory\n# ═══════════════════════════════════════════════════════════════\n\n# ── Buffers → Tabs ────────────────────────────────────────────\n# Neovim: ]b/[b (mini.bracketed), <M-Tab>, <leader>x\nmap ]b        nextTab\nmap [b        previousTab\nmap <space>x  removeTab\nmap <space>bn createTab\nmap <space>bt visitPreviousTab\nmap X         restoreTab\n\n# ── Leader-Style Commands ─────────────────────────────────────\n# Mirroring <space> leader patterns\n\n# smart open   (<leader><space>):\nmap <space><space> Vomnibar.activate      \n# find files   (<leader>ff):       \nmap <space>ff      Vomnibar.activateInNewTab  \n# recent tabs  (<leader>fr) :    \nmap <space>fr      Vomnibar.activateTabSelection   \n# bookmarks    (<leader>fc):\nmap <space>fc      Vomnibar.activateBookmarks      \n\n# ── Search ────────────────────────────────────────────────────\n# Grep style (<leader>fg)\nmap <space>fg enterFindMode\n\n# ── Link Hints ────────────────────────────────────────────────\n# f/F are Vimium defaults; adding go-to-definition style\nmap <space>ld LinkHints.activateMode\nmap <space>li LinkHints.activateModeToOpenInNewTab\n\n# ── Copy / Yank ──────────────────────────────────────────────\n# Matches <leader>fy yank-all style\nmap <space>fy copyCurrentUrl\nmap <space>fp openCopiedUrlInCurrentTab\nmap <space>fP openCopiedUrlInNewTab\n\n# ── URL Navigation ───────────────────────────────────────────\n# <leader>go opens in browser — here, navigate up the path\nmap <space>go goToRoot\nmap <space>gu goUp\n\n# ── Scroll ───────────────────────────────────────────────────\n# J/K default to tab switching — remap to full-page scroll\n# (tab switching already covered by ]b / [b)\nunmap J\nunmap K\nmap J scrollFullPageDown\nmap K scrollFullPageUp\n\n# ── Toggles ──────────────────────────────────────────────────\nmap \\z toggleViewSource\nmap \\p togglePinTab\n\n# ── Marks ────────────────────────────────────────────────────\nmap <space>sm Marks.activateCreateMode\nmap <space>gm Marks.activateGotoMode\n\n# ── Visual Mode ──────────────────────────────────────────────\nmap <space>sv enterVisualMode\nmap <space>sV enterVisualLineMode\n\n# ── Help ─────────────────────────────────────────────────────\nmap <space>h showHelp\nmap <space>k showHelp\nmap <space>? createTab https://github.com/carlisia/dotfiles/blob/main/vimium/README.md\nmap ?        showHelp",
  "newTabDestination": "browserNewTabPage",
  "regexFindMode": true,
  "searchEngines": "# ── Search Engines ─────────────────────────────────────────────\ng:   https://www.google.com/search?q=%s                            Google\nd:   https://duckduckgo.com/?q=%s                                       DuckDuckGo\n\n# ── Go ─────────────────────────────────────────────────────────\ngo:  https://pkg.go.dev/search?q=%s                                Go Packages\ngd:  https://pkg.go.dev/%s                                                 Go Docs Direct\ngp:  https://go.dev/play/p/%s                                             Go Playground\ngs:  https://gobyexample.com/#%s                                   Go By Example\n\n# ── GitHub ─────────────────────────────────────────────────────\ngh:  https://github.com/search?q=%s&type=repositories              GitHub Repos\ngi:  https://github.com/search?q=%s&type=issues                       GitHub Issues\ngc:  https://github.com/search?q=%s&type=code                        GitHub Code\ngv:  https://github.com/%s                                                            GitHub Go To Repo\n\n# ── Teleport ───────────────────────────────────────────────────\ntp:  https://github.com/gravitational/teleport/search?q=%s         Teleport Code\nti:  https://github.com/gravitational/teleport/issues?q=%s           Teleport Issues\ntd:  https://goteleport.com/docs/search/?q=%s                           Teleport Docs\n\n# ── Reference ──────────────────────────────────────────────────\nw:   https://www.wikipedia.org/w/index.php?title=Special:Search&search=%s           Wikipedia\nso:  https://stackoverflow.com/search?q=%s                                                              StackOverflow\nrd:  https://www.reddit.com/search/?q=%s                                                                  Reddit\nyt:  https://www.youtube.com/results?search_query=%s                                            YouTube\n\n# ── Usage examples (hit 'o' then type) ─────────────────────────\n#\n#   go io Reader                                     → search Go packages for io Reader\n#   gd net/http                                        → jump directly to net/http docs\n#   gv gravitational/teleport                    → jump straight to a repo\n#   gc teleport discovery                        → search code across all of GitHub\n#   tp DiscoveryService                         → search Teleport repo specifically\n#   so golang context cancel                 → StackOverflow for Go questions\n#\n#   gv is basically cd for GitHub. Type gv carlisia/dotfiles\n#   and you're there.",
  "settingsVersion": "2.4.0",
  "userDefinedLinkHintCss": "/* ══════════════════════════════════════════════════════════════\n   Vimium UI — grokkingtech.io palette\n   ══════════════════════════════════════════════════════════════ */\n\n/* ── Link Hints ──────────────────────────────────────────────── */\n\ndiv > .vimiumHintMarker {\n  background:    #1a1a1d;\n  border:        1.5px solid #a83382;\n  border-radius: 4px;\n  padding:       2px 5px;\n  box-shadow:    0 2px 8px #00000040;\n}\n\ndiv > .vimiumHintMarker span {\n  color:       #dcdcdc;\n  font-weight: bold;\n  font-size:   12px;\n  text-shadow: none;\n}\n\ndiv > .vimiumHintMarker > .matchingCharacter {\n  color: #a83382;\n}\n\n/* ── Vomnibar ────────────────────────────────────────────────── */\n\n#vomnibar {\n  background:    #1a1a1d;\n  border:        1.5px solid #2a2a2d;\n  border-radius: 8px;\n  box-shadow:    0 8px 24px #00000040;\n}\n\n#vomnibar input {\n  background:    #2a2a2d;\n  color:         #fff;\n  border:        1px solid #4f4f4f;\n  border-radius: 4px;\n}\n\n#vomnibar .vomnibarTopHalf,\n#vomnibar ul {\n  background: #1a1a1d;\n}\n\n#vomnibar li {\n  border-bottom: 1px solid #2a2a2d;\n  color:         #dcdcdc;\n}\n\n#vomnibar li .vomnibarUrl {\n  color: #5f81ff;\n}\n\n#vomnibar li .vomnibarMatch {\n  color:       #a83382;\n  font-weight: bold;\n}\n\n#vomnibar li.vomnibarSelected {\n  background:  #2a2a2d;\n  border-left: 3px solid #a83382;\n}\n\n/* ── HUD (bottom-left status bar) ────────────────────────────── */\n\ndiv.vimiumHUD {\n  background:    #1a1a1d;\n  border:        1px solid #2a2a2d;\n  border-radius: 4px;\n  box-shadow:    0 2px 8px #00000040;\n}\n\ndiv.vimiumHUD span#hud-find-input,\ndiv.vimiumHUD .vimiumHUDSearchArea {\n  color: #fff;\n}\n\ndiv.vimiumHUD .hud-find {\n  background:    #2a2a2d;\n  border-radius: 4px;\n}"
}
